{"about_index.md":"8e4249af","archives.md":"880c6cc7","courses_java_01-java语法入门_07-控制语句和流程图.md":"c2342d60","courses_java_01-java语法入门_02-第一个java程序.md":"1dca2feb","courses_java_01-java语法入门_04-程序和计算机的那点事儿.md":"4cf34224","web_forward_index.md":"e6902384","linux_tools_03-docker_02-docker 基础知识.md":"af4f5eac","linux_tools_05-regexp_01-常用语法.md":"0af86246","courses_java_01-java语法入门_09-switch选择结构.md":"d902e9d1","web_forward_01-nodejs_07-nodejs大纲.md":"fbe7b769","web_forward_04-http_02-headers.md":"9f9b3130","linux_linux_index.md":"cb46be6f","web_forward_01-nodejs_04-global.md":"46648c3a","courses_java_01-java语法入门_08-if选择结构.md":"6fca1be0","web_basics_01-javascript_04-dom.md":"3e451f85","about_me.md":"d6d5d56b","web_forward_01-nodejs_05-process.md":"c8431d4e","web_forward_01-nodejs_01-file_upload.md":"e9e9a2e5","web_basics_05-es6_01-es6归纳总结.md":"475ef35b","web_forward_01-nodejs_02-fs.md":"20776c2d","courses_java_02-java面向对象_01-类和对象.md":"a6b02bf1","courses_java_01-java语法入门_01-开发环境搭建.md":"884a83f0","courses_java_01-java语法入门_11-多重循环.md":"233645c0","web_basics_01-javascript_03-bom.md":"0798ee8b","courses_java_01-java语法入门_05-变量和常量.md":"8884473f","web_forward_03-webpack_01-build_process.md":"36075adf","web_basics_04-html_01-html5基本使用.md":"8506ea90","linux_tools_02-nginx_01-常用命令 _ 配置文件.md":"ce84051e","linux_tools_index.md":"78c53468","courses_mybatis_02-mybatis-plus基础_01-快速入门.md":"9d9749bb","courses_mysql_03-附录_01-centos安装mysql.md":"b57ed026","web_basics_03-css_02-grid 网格布局.md":"f70ec6e0","linux_linux_01-shell_01-linux常用命令.md":"bca33536","web_basics_03-css_03-position 定位.md":"817bee11","courses_java_index.md":"1c496f92","web_basics_index.md":"af6b6f2e","web_basics_01-javascript_01-array_api.md":"40cc66c3","courses_java_01-java语法入门_13-一维数组.md":"4df5d555","web_basics_03-css_07-em_px_rem_vh_vw 单位.md":"f3622888","linux_tools_04-kubernetes_02-k8s-cmd.md":"a536e863","linux_db_01-mysql_01-数据类型.md":"53eaae7b","web_interview_index.md":"86ef00d3","linux_db_01-mysql_03-sql.md":"fb35ef46","courses_mybatis_01-mybatis基础_06-sql映射文件之自定义映射元素.md":"4977b195","courses_java_01-java语法入门_06-常用的运算符.md":"5f7ea940","linux_db_01-mysql_02-mysq操作.md":"12b20d16","web_basics_03-css_05-伪类 _ 伪元素.md":"b0e6a244","courses_mybatis_02-mybatis-plus基础_02-增删改操作.md":"b369217f","linux_tools_03-docker_03-docker 镜像安装.md":"7222d135","web_forward_04-http_03-status.md":"86bbc6f2","web_basics_03-css_08-grid.md":"4f928bfe","courses_mybatis_02-mybatis-plus基础_03-简单查询操作.md":"ebf7a553","courses_mybatis_index.md":"3191279b","courses_java_03-java高级特性_01-集合与泛型-1.md":"3a0b60a7","courses_java_04-附录_01-centos安装jdk.md":"ea90f2a7","courses_mysql_index.md":"7accd1b8","linux_tools_01-git_01-git常用命令.md":"0ed0266e","courses_mysql_03-附录_02-docker安装mysql.md":"3afa7b57","courses_java_01-java语法入门_12-程序调试入门.md":"3a106a4e","courses_mybatis_02-mybatis-plus基础_04-条件构造器.md":"4bf7054f","courses_java_01-java语法入门_10-循环结构.md":"0d9439ae","web_forward_01-nodejs_06-middleware.md":"bf20309d","web_basics_03-css_06-selector 选择器.md":"fed6da28","linux_tools_04-kubernetes_01-k8s.md":"a1efa494","courses_mybatis_02-mybatis-plus基础_05-代码生成器.md":"9544b134","linux_db_index.md":"4beafd00","web_basics_03-css_01-flex 弹性布局.md":"01d86b75","courses_mybatis_01-mybatis基础_07-sql映射文件之缓存元素.md":"9e939a42","web_basics_02-typescript_01-typescript快速上手.md":"f60280c1","linux_db_02-clickhouse_01-基础知识.md":"4c81f2ac","courses_mybatis_01-mybatis基础_08-动态sql.md":"10536290","courses_mybatis_01-mybatis基础_05-sql映射文件之增删改元素.md":"64459b51","linux_linux_02-vim_01-vim编辑器.md":"ae75098c","index.md":"2e662e4a","web_interview_01-interview_02-html.md":"211cc68b","courses_mybatis_01-mybatis基础_04-sql映射文件之查询元素.md":"49f6adc4","web_forward_04-http_01-http.md":"5c3bb571","courses_java_01-java语法入门_03-初识eclipse.md":"ce7a1afe","web_basics_01-javascript_02-string_api.md":"60da6b32","courses_mybatis_01-mybatis基础_02-核心对象.md":"44cd2663","courses_java_01-java语法入门_14-多维数组.md":"a42172ed","linux_tools_03-docker_01-docker 常用命令.md":"cc6d24f9","courses_mysql_01-mysql基础_01-mysql安装与配置.md":"96c80fac","web_interview_01-interview_04-计算机网络.md":"456c0a39","courses_mybatis_01-mybatis基础_01-快速入门.md":"f1afdff3","web_interview_01-interview_03-css.md":"65aeaa31","courses_mybatis_01-mybatis基础_03-核心配置文件.md":"40d71479","web_interview_01-interview_01-javascript.md":"99ff3611"}
